testexprep/__init__.py
testexprep/common.py
testexprep-0.0.1.dist-info/LICENSE
testexprep-0.0.1.dist-info/METADATA
testexprep-0.0.1.dist-info/WHEEL
testexprep-0.0.1.dist-info/top_level.txt
testexprep-0.0.1.dist-info/RECORD
